{
    "id": 42,
    "distance": 1.9607033332325325,
    "children": [
        {
            "id": 21,
            "label": "send voice messaging"
        },
        {
            "id": 41,
            "distance": 0.0,
            "children": [
                {
                    "id": 20,
                    "label": "quiet good good messaging app"
                },
                {
                    "id": 40,
                    "distance": 0.0,
                    "children": [
                        {
                            "id": 19,
                            "label": "yet generic messaging app"
                        },
                        {
                            "id": 39,
                            "distance": 0.0,
                            "children": [
                                {
                                    "id": 18,
                                    "label": "exceptional messaging app"
                                },
                                {
                                    "id": 38,
                                    "distance": 0.0,
                                    "children": [
                                        {
                                            "id": 17,
                                            "label": "seriously good messaging app"
                                        },
                                        {
                                            "id": 37,
                                            "distance": 0.0,
                                            "children": [
                                                {
                                                    "id": 16,
                                                    "label": "voice messaging"
                                                },
                                                {
                                                    "id": 36,
                                                    "distance": 0.0,
                                                    "children": [
                                                        {
                                                            "id": 15,
                                                            "label": "good fast and safe messaging app"
                                                        },
                                                        {
                                                            "id": 35,
                                                            "distance": 0.0,
                                                            "children": [
                                                                {
                                                                    "id": 14,
                                                                    "label": "very good messaging app"
                                                                },
                                                                {
                                                                    "id": 34,
                                                                    "distance": 0.0,
                                                                    "children": [
                                                                        {
                                                                            "id": 13,
                                                                            "label": "nice novice messaging"
                                                                        },
                                                                        {
                                                                            "id": 33,
                                                                            "distance": 0.0,
                                                                            "children": [
                                                                                {
                                                                                    "id": 12,
                                                                                    "label": "bad messaging app"
                                                                                },
                                                                                {
                                                                                    "id": 32,
                                                                                    "distance": 0.0,
                                                                                    "children": [
                                                                                        {
                                                                                            "id": 11,
                                                                                            "label": "excellent messaging app"
                                                                                        },
                                                                                        {
                                                                                            "id": 31,
                                                                                            "distance": 0.0,
                                                                                            "children": [
                                                                                                {
                                                                                                    "id": 10,
                                                                                                    "label": "very good and convenient messaging app"
                                                                                                },
                                                                                                {
                                                                                                    "id": 30,
                                                                                                    "distance": 0.0,
                                                                                                    "children": [
                                                                                                        {
                                                                                                            "id": 9,
                                                                                                            "label": "no doubt good messaging app"
                                                                                                        },
                                                                                                        {
                                                                                                            "id": 29,
                                                                                                            "distance": 0.0,
                                                                                                            "children": [
                                                                                                                {
                                                                                                                    "id": 8,
                                                                                                                    "label": "good messaging app"
                                                                                                                },
                                                                                                                {
                                                                                                                    "id": 28,
                                                                                                                    "distance": 0.0,
                                                                                                                    "children": [
                                                                                                                        {
                                                                                                                            "id": 7,
                                                                                                                            "label": "great free messaging app"
                                                                                                                        },
                                                                                                                        {
                                                                                                                            "id": 27,
                                                                                                                            "distance": 0.0,
                                                                                                                            "children": [
                                                                                                                                {
                                                                                                                                    "id": 6,
                                                                                                                                    "label": "great messaging app"
                                                                                                                                },
                                                                                                                                {
                                                                                                                                    "id": 26,
                                                                                                                                    "distance": 0.0,
                                                                                                                                    "children": [
                                                                                                                                        {
                                                                                                                                            "id": 5,
                                                                                                                                            "label": "easy messaging"
                                                                                                                                        },
                                                                                                                                        {
                                                                                                                                            "id": 25,
                                                                                                                                            "distance": 0.0,
                                                                                                                                            "children": [
                                                                                                                                                {
                                                                                                                                                    "id": 4,
                                                                                                                                                    "label": "really great messaging app"
                                                                                                                                                },
                                                                                                                                                {
                                                                                                                                                    "id": 24,
                                                                                                                                                    "distance": 0.0,
                                                                                                                                                    "children": [
                                                                                                                                                        {
                                                                                                                                                            "id": 3,
                                                                                                                                                            "label": "just good messaging app"
                                                                                                                                                        },
                                                                                                                                                        {
                                                                                                                                                            "id": 23,
                                                                                                                                                            "distance": 0.0,
                                                                                                                                                            "children": [
                                                                                                                                                                {
                                                                                                                                                                    "id": 2,
                                                                                                                                                                    "label": "easily good messaging app"
                                                                                                                                                                },
                                                                                                                                                                {
                                                                                                                                                                    "id": 22,
                                                                                                                                                                    "distance": 0.0,
                                                                                                                                                                    "children": [
                                                                                                                                                                        {
                                                                                                                                                                            "id": 0,
                                                                                                                                                                            "label": "very simple messaging app"
                                                                                                                                                                        },
                                                                                                                                                                        {
                                                                                                                                                                            "id": 1,
                                                                                                                                                                            "label": "very nice messaging app"
                                                                                                                                                                        }
                                                                                                                                                                    ]
                                                                                                                                                                }
                                                                                                                                                            ]
                                                                                                                                                        }
                                                                                                                                                    ]
                                                                                                                                                }
                                                                                                                                            ]
                                                                                                                                        }
                                                                                                                                    ]
                                                                                                                                }
                                                                                                                            ]
                                                                                                                        }
                                                                                                                    ]
                                                                                                                }
                                                                                                            ]
                                                                                                        }
                                                                                                    ]
                                                                                                }
                                                                                            ]
                                                                                        }
                                                                                    ]
                                                                                }
                                                                            ]
                                                                        }
                                                                    ]
                                                                }
                                                            ]
                                                        }
                                                    ]
                                                }
                                            ]
                                        }
                                    ]
                                }
                            ]
                        }
                    ]
                }
            ]
        }
    ]
}